{
  "id": "EARN_1767521690883",
  "type": "earning",
  "data": {
    "earning_id": "EARN_1767521690883",
    "amount": 159,
    "currency": "USD",
    "occurred_at": "2026-01-04T10:14:50.883Z",
    "source": "Swarm Agent AGENT_00148 (Content Writer)",
    "beneficiary": "younestsouli2019@gmail.com",
    "status": "pending_payout",
    "revenue_event_id": "PSP_1767521690807_AGENT_00148",
    "metadata": {
      "recipient_type": "owner",
      "autonomous": true,
      "ingested_at": "2026-01-04T10:14:50.883Z"
    },
    "created_at": "2026-01-04T10:14:50.883Z"
  },
  "saved_at": "2026-01-04T10:14:50.883Z",
  "autonomous": true
}