{
  "id": "EARN_1767521691959",
  "type": "earning",
  "data": {
    "earning_id": "EARN_1767521691959",
    "amount": 497,
    "currency": "USD",
    "occurred_at": "2026-01-04T10:14:51.959Z",
    "source": "Swarm Agent AGENT_01629 (Research Analyst)",
    "beneficiary": "younestsouli2019@gmail.com",
    "status": "pending_payout",
    "revenue_event_id": "PSP_1767521690807_AGENT_01629",
    "metadata": {
      "recipient_type": "owner",
      "autonomous": true,
      "ingested_at": "2026-01-04T10:14:51.959Z"
    },
    "created_at": "2026-01-04T10:14:51.959Z"
  },
  "saved_at": "2026-01-04T10:14:51.959Z",
  "autonomous": true
}