{
  "id": "EARN_1767521692326",
  "type": "earning",
  "data": {
    "earning_id": "EARN_1767521692326",
    "amount": 153,
    "currency": "USD",
    "occurred_at": "2026-01-04T10:14:52.326Z",
    "source": "Swarm Agent AGENT_02200 (Research Analyst)",
    "beneficiary": "younestsouli2019@gmail.com",
    "status": "pending_payout",
    "revenue_event_id": "PSP_1767521690807_AGENT_02200",
    "metadata": {
      "recipient_type": "owner",
      "autonomous": true,
      "ingested_at": "2026-01-04T10:14:52.326Z"
    },
    "created_at": "2026-01-04T10:14:52.326Z"
  },
  "saved_at": "2026-01-04T10:14:52.327Z",
  "autonomous": true
}